re_cloud/__init__.py
re_cloud/command_line.py
re_cloud/constants.py
re_cloud/flags.py
re_cloud/render.py
re_cloud/tracking.py
re_cloud/upload.py
re_cloud/utils.py
re_cloud/version.py
re_cloud/config/__init__.py
re_cloud/config/system.py
re_cloud/config/utils.py
re_cloud/config/validate.py
re_cloud/config/yaml_utils.py
re_cloud/templates/__init__.py
re_cloud/templates/markdown.html.j2
re_cloud/templates/pdf.html.j2
re_cloud-0.3.0.dist-info/METADATA
re_cloud-0.3.0.dist-info/WHEEL
re_cloud-0.3.0.dist-info/entry_points.txt
re_cloud-0.3.0.dist-info/top_level.txt
re_cloud-0.3.0.dist-info/RECORD
